[
  {
    "sku": "RizwanX-4597",
    "our_title": "Green Giant FreshLock Variety Pack – 8 Shelf-Stable Canned Vegetables",
    "walmart_item_id": "6ZQ9PM9P7JC2",
    "category": "Dry",
    "retail_search_query": "Green Giant FreshLock Variety Pack 8 cans shelf stable",
    "base_unit": "Green Giant FreshLock Variety Pack 8 ct cans",
    "brand": "Green Giant",
    "product_line": "FreshLock",
    "flavor": "variety",
    "size": "8 pack",
    "container_type": "can",
    "units_in_listing": 1,
    "is_bundle": true,
    "components": [
      {
        "product": "Green Giant Whole Kernel Sweet Corn",
        "flavor": "Sweet Corn",
        "size": "15.25 oz",
        "qty": 2
      },
      {
        "product": "Green Giant Cut Green Beans",
        "flavor": "Cut Green Beans",
        "size": "14.5 oz",
        "qty": 2
      },
      {
        "product": "Green Giant Sweet Peas",
        "flavor": "Sweet Peas",
        "size": "15 oz",
        "qty": 2
      },
      {
        "product": "Green Giant Mixed Vegetables",
        "flavor": "Mixed Vegetables",
        "size": "15 oz",
        "qty": 2
      }
    ],
    "confidence": 0.62,
    "notes": "Variety pack containing 8 cans of assorted Green Giant vegetables. The exact flavor breakdown is estimated based on typical Green Giant variety packs (commonly corn, green beans, sweet peas, and mixed vegetables, 2 each). Without being able to clearly read every label in the photo, the specific varieties and exact sizes may vary slightly. This is sold as a single variety pack unit containing multiple different products, making it a bundle."
  },
  {
    "sku": "RizwanX-3877",
    "our_title": "La Abuela Ready to Cook Burrito Size Flour Tortillas 18.5 oz 12 Count (Pack of 2)",
    "walmart_item_id": null,
    "category": "Dry",
    "retail_search_query": "La Abuela Ready to Cook Burrito Size Flour Tortillas 18.5 oz 12 Count",
    "base_unit": "La Abuela Ready to Cook Burrito Size Flour Tortillas 18.5 oz 12 Count bag",
    "brand": "La Abuela",
    "product_line": "Ready to Cook Burrito Size Flour Tortillas",
    "flavor": "Flour",
    "size": "18.5 oz",
    "container_type": "bag",
    "units_in_listing": 2,
    "is_bundle": false,
    "components": [],
    "confidence": 0.9,
    "notes": "Pack of 2 listing. Each bag contains 12 burrito-size flour tortillas at 18.5 oz per bag. No photo provided to confirm container type; assuming standard tortilla bag packaging."
  }
]