{
  "engine" : "apple-vision-accurate-literal",
  "images" : [
    {
      "height" : 1800,
      "observations" : [
        {
          "bounding_box" : {
            "height" : 0.024096875720553967,
            "width" : 0.06957962459988065,
            "x" : 0.1339740669014761,
            "y" : 0.8499069124703305
          },
          "confidence" : 0.3,
          "text" : "LОНИЗСИ РАСККА ЛВ СРОНЕВ3И9"
        },
        {
          "bounding_box" : {
            "height" : 0.030722465515136688,
            "width" : 0.13661315070258245,
            "x" : 0.08639770647042838,
            "y" : 0.818778774258739
          },
          "confidence" : 0.3,
          "text" : "EpŞCED*"
        },
        {
          "bounding_box" : {
            "height" : 0.020613694720798104,
            "width" : 0.05668604532877605,
            "x" : 0.2122093028806701,
            "y" : 0.8299418606839754
          },
          "confidence" : 0.3,
          "text" : "Bitea UP rp"
        },
        {
          "bounding_box" : {
            "height" : 0.02777777777777779,
            "width" : 0.15116278754340284,
            "x" : 0.4098837240189962,
            "y" : 0.8211111109259963
          },
          "confidence" : 0.3,
          "text" : "Elpg/CED -B"
        },
        {
          "bounding_box" : {
            "height" : 0.02618862999810112,
            "width" : 0.03924418555365672,
            "x" : 0.5552325581056468,
            "y" : 0.8255555554893845
          },
          "confidence" : 0.3,
          "text" : "ОР р"
        },
        {
          "bounding_box" : {
            "height" : 0.030523255666097038,
            "width" : 0.1351744164360894,
            "x" : 0.7325581414185832,
            "y" : 0.8197674422396259
          },
          "confidence" : 0.3,
          "text" : "1APSUCED3"
        },
        {
          "bounding_box" : {
            "height" : 0.027855296664767826,
            "width" : 0.0625,
            "x" : 0.8561046510029071,
            "y" : 0.8238888887359398
          },
          "confidence" : 0.3,
          "text" : "Bitea DP. SP"
        },
        {
          "bounding_box" : {
            "height" : 0.018895348442925286,
            "width" : 0.026162789662679042,
            "x" : 0.14825581420935818,
            "y" : 0.806686046577956
          },
          "confidence" : 1,
          "text" : "BUTAR"
        },
        {
          "bounding_box" : {
            "height" : 0.018895348442925397,
            "width" : 0.026162789662679042,
            "x" : 0.472383721360521,
            "y" : 0.8066860465198163
          },
          "confidence" : 0.5,
          "text" : "BUTAR"
        },
        {
          "bounding_box" : {
            "height" : 0.02034883711073132,
            "width" : 0.024709300994873118,
            "x" : 0.7965116286995112,
            "y" : 0.8066860468152739
          },
          "confidence" : 1,
          "text" : "ВUТТЯ"
        },
        {
          "bounding_box" : {
            "height" : 0.017900502946641694,
            "width" : 0.0947814687093099,
            "x" : 0.12775461515661807,
            "y" : 0.6720090508970818
          },
          "confidence" : 1,
          "text" : "PEPPERIDGE FARM"
        },
        {
          "bounding_box" : {
            "height" : 0.01744185977511936,
            "width" : 0.09447674221462671,
            "x" : 0.4520348858512622,
            "y" : 0.6715116280339519
          },
          "confidence" : 1,
          "text" : "PEPPERIDGE FARM"
        },
        {
          "bounding_box" : {
            "height" : 0.017853604422675362,
            "width" : 0.09455189175075962,
            "x" : 0.7761252178599496,
            "y" : 0.6713057564912048
          },
          "confidence" : 1,
          "text" : "PEPPERIDGE FARM"
        },
        {
          "bounding_box" : {
            "height" : 0.00872092988755968,
            "width" : 0.04360465155707466,
            "x" : 0.13517441913425335,
            "y" : 0.6598837211511814
          },
          "confidence" : 0.3,
          "text" : "IXTD.26209"
        },
        {
          "bounding_box" : {
            "height" : 0.00872092988755968,
            "width" : 0.04651162465413411,
            "x" : 0.45930232643262286,
            "y" : 0.6598837210058326
          },
          "confidence" : 0.3,
          "text" : "ITD.46209"
        },
        {
          "bounding_box" : {
            "height" : 0.007267441749572612,
            "width" : 0.03343023088243269,
            "x" : 0.7834302339531635,
            "y" : 0.6598837210583532
          },
          "confidence" : 0.3,
          "text" : "IXTD.45"
        },
        {
          "bounding_box" : {
            "height" : 0.007299741639031243,
            "width" : 0.0726744164360894,
            "x" : 0.1395348838967809,
            "y" : 0.6482558139544288
          },
          "confidence" : 1,
          "text" : "BAKERY CLASSICS"
        },
        {
          "bounding_box" : {
            "height" : 0.007299741374121704,
            "width" : 0.07267441643608935,
            "x" : 0.4636627926903855,
            "y" : 0.6482558140634403
          },
          "confidence" : 1,
          "text" : "BAKERY CLASSICS"
        },
        {
          "bounding_box" : {
            "height" : 0.007299741374121704,
            "width" : 0.0726744164360894,
            "x" : 0.7863372115978468,
            "y" : 0.648255814081609
          },
          "confidence" : 1,
          "text" : "BAKERY CLASSICS"
        },
        {
          "bounding_box" : {
            "height" : 0.01795744789971243,
            "width" : 0.07424752977159288,
            "x" : 0.12930065327171844,
            "y" : 0.56369569450633
          },
          "confidence" : 1,
          "text" : "8 TOP SLICED"
        },
        {
          "bounding_box" : {
            "height" : 0.0029069768057928824,
            "width" : 0.026162789662679042,
            "x" : 0.21947674463086977,
            "y" : 0.5813953488144809
          },
          "confidence" : 0.3,
          "text" : "нAОИIИ"
        },
        {
          "bounding_box" : {
            "height" : 0.011627906163533486,
            "width" : 0.024709300994873035,
            "x" : 0.2194767447605577,
            "y" : 0.5683139537496286
          },
          "confidence" : 1,
          "text" : "REAL"
        },
        {
          "bounding_box" : {
            "height" : 0.007267441749572723,
            "width" : 0.02906976699829103,
            "x" : 0.16133720903961418,
            "y" : 0.5624999999827718
          },
          "confidence" : 1,
          "text" : "BUTTER"
        },
        {
          "bounding_box" : {
            "height" : 0.01162790722317153,
            "width" : 0.033430233001709,
            "x" : 0.21511627912656794,
            "y" : 0.5581395348331817
          },
          "confidence" : 1,
          "text" : "BUTTER"
        },
        {
          "bounding_box" : {
            "height" : 0.014534883499145557,
            "width" : 0.011627906163533541,
            "x" : 0.45348837242695417,
            "y" : 0.5639534886646713
          },
          "confidence" : 1,
          "text" : "8"
        },
        {
          "bounding_box" : {
            "height" : 0.011899224917093942,
            "width" : 0.06540697733561202,
            "x" : 0.4622093024970611,
            "y" : 0.5697674417995438
          },
          "confidence" : 1,
          "text" : "TOP SLICED"
        },
        {
          "bounding_box" : {
            "height" : 0.01162790722317164,
            "width" : 0.024709300994873007,
            "x" : 0.5436046520046399,
            "y" : 0.5683139534274507
          },
          "confidence" : 1,
          "text" : "REAL"
        },
        {
          "bounding_box" : {
            "height" : 0.014534883499145446,
            "width" : 0.010174418555365605,
            "x" : 0.7776162790217359,
            "y" : 0.5639534886283342
          },
          "confidence" : 1,
          "text" : "8"
        },
        {
          "bounding_box" : {
            "height" : 0.011899224387274865,
            "width" : 0.06540697309705945,
            "x" : 0.7863372103083017,
            "y" : 0.5697674421580587
          },
          "confidence" : 1,
          "text" : "TOP SLICED"
        },
        {
          "bounding_box" : {
            "height" : 0.011627906163533597,
            "width" : 0.026162789662679042,
            "x" : 0.8662790699579047,
            "y" : 0.568313953822303
          },
          "confidence" : 1,
          "text" : "REAL"
        },
        {
          "bounding_box" : {
            "height" : 0.0029069768057929934,
            "width" : 0.027616278330485078,
            "x" : 0.8662790700644086,
            "y" : 0.5813953488140557
          },
          "confidence" : 0.3,
          "text" : "НAGMIИ"
        },
        {
          "bounding_box" : {
            "height" : 0.007267441749572612,
            "width" : 0.029069766998291058,
            "x" : 0.4854651168642266,
            "y" : 0.562500000109952
          },
          "confidence" : 1,
          "text" : "BUTTER"
        },
        {
          "bounding_box" : {
            "height" : 0.010174418555365716,
            "width" : 0.03343023300170911,
            "x" : 0.5392441855461416,
            "y" : 0.5581395348478015
          },
          "confidence" : 1,
          "text" : "BUTTER"
        },
        {
          "bounding_box" : {
            "height" : 0.007267441749572834,
            "width" : 0.027616278330485078,
            "x" : 0.8095930235568182,
            "y" : 0.5625000000756335
          },
          "confidence" : 1,
          "text" : "BUTTER"
        },
        {
          "bounding_box" : {
            "height" : 0.01024972067938923,
            "width" : 0.03345307244194884,
            "x" : 0.8633606735896887,
            "y" : 0.5581018836756324
          },
          "confidence" : 1,
          "text" : "BUTTER"
        },
        {
          "bounding_box" : {
            "height" : 0.007454780472649469,
            "width" : 0.04651162465413411,
            "x" : 0.15261628147138254,
            "y" : 0.5477777776841137
          },
          "confidence" : 1,
          "text" : "HOT DOG BUNS"
        },
        {
          "bounding_box" : {
            "height" : 0.007454780207740042,
            "width" : 0.04505813598632813,
            "x" : 0.47674418706982047,
            "y" : 0.5477777778036743
          },
          "confidence" : 1,
          "text" : "HOT DOG BUNS"
        },
        {
          "bounding_box" : {
            "height" : 0.007454780207740042,
            "width" : 0.04505814022488064,
            "x" : 0.8008720921150306,
            "y" : 0.5477777778218429
          },
          "confidence" : 1,
          "text" : "HOT DOG BUNS"
        },
        {
          "bounding_box" : {
            "height" : 0.008888889153798485,
            "width" : 0.03924418555365669,
            "x" : 0.1177325590400321,
            "y" : 0.5261111110425076
          },
          "confidence" : 0.3,
          "text" : "srW IEpsany"
        },
        {
          "bounding_box" : {
            "height" : 0.008888888888888835,
            "width" : 0.0406976742214627,
            "x" : 0.44040697616446245,
            "y" : 0.5261111111620683
          },
          "confidence" : 0.3,
          "text" : "BrW Hosgiy"
        },
        {
          "bounding_box" : {
            "height" : 0.007267441749572834,
            "width" : 0.04651162465413411,
            "x" : 0.4404069791458011,
            "y" : 0.5363372094304462
          },
          "confidence" : 0.3,
          "text" : "Wiacneo"
        },
        {
          "bounding_box" : {
            "height" : 0.00924490186903204,
            "width" : 0.03935728708902997,
            "x" : 0.7644783327101342,
            "y" : 0.5259008048002102
          },
          "confidence" : 0.3,
          "text" : "MиIHNоту"
        },
        {
          "bounding_box" : {
            "height" : 0.007267441749572834,
            "width" : 0.04215116288926868,
            "x" : 0.7645348843741641,
            "y" : 0.5363372094304462
          },
          "confidence" : 0.3,
          "text" : "WIкACRAAON"
        },
        {
          "bounding_box" : {
            "height" : 0.018211354149712422,
            "width" : 0.04334815131293407,
            "x" : 0.4842681261313612,
            "y" : 0.46058481511835936
          },
          "confidence" : 0.3,
          "text" : "ВаТСРОНЕВзИА"
        },
        {
          "bounding_box" : {
            "height" : 0.03537706163194443,
            "width" : 0.13541806538899742,
            "x" : 0.08482220730914712,
            "y" : 0.4212004251409126
          },
          "confidence" : 0.3,
          "text" : "El3PSICED-"
        },
        {
          "bounding_box" : {
            "height" : 0.032075671090020075,
            "width" : 0.1502638244628906,
            "x" : 0.4096064596266154,
            "y" : 0.42291565311933277
          },
          "confidence" : 0.3,
          "text" : "ElPSICED di"
        },
        {
          "bounding_box" : {
            "height" : 0.01744185977511936,
            "width" : 0.058139533996582005,
            "x" : 0.8575581393970578,
            "y" : 0.4360465119438356
          },
          "confidence" : 0.3,
          "text" : "ВлEaОР гр"
        },
        {
          "bounding_box" : {
            "height" : 0.01744185977511936,
            "width" : 0.026162789662679042,
            "x" : 0.14825581420935818,
            "y" : 0.4113372095310449
          },
          "confidence" : 0.5,
          "text" : "BUTR"
        },
        {
          "bounding_box" : {
            "height" : 0.018895348442925286,
            "width" : 0.026162789662679042,
            "x" : 0.472383721360521,
            "y" : 0.4113372093105141
          },
          "confidence" : 0.3,
          "text" : "BUTAR"
        },
        {
          "bounding_box" : {
            "height" : 0.019121446609497106,
            "width" : 0.024709300994873118,
            "x" : 0.7965116284451508,
            "y" : 0.41111111109670395
          },
          "confidence" : 0.3,
          "text" : "BUT AS"
        },
        {
          "bounding_box" : {
            "height" : 0.01820047378540035,
            "width" : 0.09606525844997829,
            "x" : 0.12783946475730892,
            "y" : 0.27578348407419273
          },
          "confidence" : 1,
          "text" : "PEPPERIDGE FARM"
        },
        {
          "bounding_box" : {
            "height" : 0.01749353991614455,
            "width" : 0.09738371955023867,
            "x" : 0.4505813972561306,
            "y" : 0.27611111090164775
          },
          "confidence" : 1,
          "text" : "PEPPERIDGE FARM"
        },
        {
          "bounding_box" : {
            "height" : 0.01617693848080104,
            "width" : 0.09450847201877177,
            "x" : 0.776146927962305,
            "y" : 0.27752199612497686
          },
          "confidence" : 1,
          "text" : "PEPPERIDGE FARM"
        },
        {
          "bounding_box" : {
            "height" : 0.007267441749572723,
            "width" : 0.04069767422146267,
            "x" : 0.1351744193815167,
            "y" : 0.2645348838490509
          },
          "confidence" : 0.3,
          "text" : "EXTD.4670"
        },
        {
          "bounding_box" : {
            "height" : 0.00872092988755968,
            "width" : 0.045058135986328185,
            "x" : 0.4593023266047041,
            "y" : 0.26453488379653034
          },
          "confidence" : 0.3,
          "text" : "тxтD.26708"
        },
        {
          "bounding_box" : {
            "height" : 0.009038806491427964,
            "width" : 0.04076460520426439,
            "x" : 0.7819432788912491,
            "y" : 0.26437594573608214
          },
          "confidence" : 0.3,
          "text" : "IXто. 4620"
        },
        {
          "bounding_box" : {
            "height" : 0.0029069765408833437,
            "width" : 0.014534882439507402,
            "x" : 0.844476745553502,
            "y" : 0.26744186056676755
          },
          "confidence" : 0.3,
          "text" : "3833"
        },
        {
          "bounding_box" : {
            "height" : 0.007396640777587837,
            "width" : 0.07412790086534288,
            "x" : 0.13953488801209596,
            "y" : 0.25277777784429156
          },
          "confidence" : 1,
          "text" : "BAKERY CLASSICS"
        },
        {
          "bounding_box" : {
            "height" : 0.007396640777587837,
            "width" : 0.07267441643608935,
            "x" : 0.4636627926903855,
            "y" : 0.2527777778261229
          },
          "confidence" : 1,
          "text" : "BAKERY CLASSICS"
        },
        {
          "bounding_box" : {
            "height" : 0.007396640777587837,
            "width" : 0.0726744164360894,
            "x" : 0.7863372115978468,
            "y" : 0.25277777784429156
          },
          "confidence" : 1,
          "text" : "BAKERY CLASSICS"
        },
        {
          "bounding_box" : {
            "height" : 0.01777777777777778,
            "width" : 0.0755813937717014,
            "x" : 0.12936046666066092,
            "y" : 0.16833333340032697
          },
          "confidence" : 1,
          "text" : "8 TOP SLICED"
        },
        {
          "bounding_box" : {
            "height" : 0.0029069768057928824,
            "width" : 0.026162789662679042,
            "x" : 0.21947674463086977,
            "y" : 0.1860465116051785
          },
          "confidence" : 0.3,
          "text" : "НАОИІИ"
        },
        {
          "bounding_box" : {
            "height" : 0.012280658086140872,
            "width" : 0.025009678734673385,
            "x" : 0.2207800446021448,
            "y" : 0.17263874077592167
          },
          "confidence" : 1,
          "text" : "REAL"
        },
        {
          "bounding_box" : {
            "height" : 0.018114674886067772,
            "width" : 0.07428332010904942,
            "x" : 0.4534106650774096,
            "y" : 0.1682682438110441
          },
          "confidence" : 1,
          "text" : "8 TOP SLICED"
        },
        {
          "bounding_box" : {
            "height" : 0.0029069765408833437,
            "width" : 0.027616276211208768,
            "x" : 0.5421511656007909,
            "y" : 0.18604651172955833
          },
          "confidence" : 0.3,
          "text" : "НADVIM"
        },
        {
          "bounding_box" : {
            "height" : 0.01162790722317164,
            "width" : 0.024709300994873007,
            "x" : 0.5436046520046399,
            "y" : 0.17296511621814847
          },
          "confidence" : 1,
          "text" : "REAL"
        },
        {
          "bounding_box" : {
            "height" : 0.007267441749572834,
            "width" : 0.029069766998291058,
            "x" : 0.4854651168642266,
            "y" : 0.16715116290064969
          },
          "confidence" : 1,
          "text" : "BUTTER"
        },
        {
          "bounding_box" : {
            "height" : 0.014534883499145557,
            "width" : 0.010174418555365605,
            "x" : 0.7776162790217359,
            "y" : 0.16860465141903203
          },
          "confidence" : 1,
          "text" : "8"
        },
        {
          "bounding_box" : {
            "height" : 0.011830659442477742,
            "width" : 0.05817974514431423,
            "x" : 0.793584546613683,
            "y" : 0.17431722847846332
          },
          "confidence" : 1,
          "text" : "TOP SLICED"
        },
        {
          "bounding_box" : {
            "height" : 0.0029069768057928824,
            "width" : 0.029069766998291002,
            "x" : 0.8648255815482842,
            "y" : 0.18604651160475338
          },
          "confidence" : 0.3,
          "text" : "НAОИIИ"
        },
        {
          "bounding_box" : {
            "height" : 0.011627906163533486,
            "width" : 0.026162789662679042,
            "x" : 0.8662790706119745,
            "y" : 0.1729651167220123
          },
          "confidence" : 1,
          "text" : "REAL"
        },
        {
          "bounding_box" : {
            "height" : 0.007267441749572723,
            "width" : 0.027616278330485022,
            "x" : 0.1627906979713854,
            "y" : 0.16715116286526877
          },
          "confidence" : 1,
          "text" : "BUTTER"
        },
        {
          "bounding_box" : {
            "height" : 0.010174418555365716,
            "width" : 0.034883719550238695,
            "x" : 0.21511628019581086,
            "y" : 0.16279069775356725
          },
          "confidence" : 1,
          "text" : "BUTTER"
        },
        {
          "bounding_box" : {
            "height" : 0.010174418555365716,
            "width" : 0.033430233001709,
            "x" : 0.5392441857520525,
            "y" : 0.1627906977211796
          },
          "confidence" : 1,
          "text" : "BUTTER"
        },
        {
          "bounding_box" : {
            "height" : 0.007267441749572723,
            "width" : 0.027616278330485078,
            "x" : 0.8095930235568182,
            "y" : 0.16715116286633125
          },
          "confidence" : 1,
          "text" : "BUTTER"
        },
        {
          "bounding_box" : {
            "height" : 0.010284400516086145,
            "width" : 0.03491564008924697,
            "x" : 0.8619026447807683,
            "y" : 0.16273570665905635
          },
          "confidence" : 1,
          "text" : "BUTTER"
        },
        {
          "bounding_box" : {
            "height" : 0.007383720874786448,
            "width" : 0.04651162465413411,
            "x" : 0.15261628147138254,
            "y" : 0.152616279197888
          },
          "confidence" : 1,
          "text" : "HOT DOG BUNS"
        },
        {
          "bounding_box" : {
            "height" : 0.007383720874786448,
            "width" : 0.046511624654134165,
            "x" : 0.4767441884481267,
            "y" : 0.152616279197888
          },
          "confidence" : 1,
          "text" : "HOT DOG BUNS"
        },
        {
          "bounding_box" : {
            "height" : 0.007383720874786448,
            "width" : 0.046511624654134165,
            "x" : 0.7994186070527778,
            "y" : 0.152616279197888
          },
          "confidence" : 1,
          "text" : "HOT DOG BUNS"
        },
        {
          "bounding_box" : {
            "height" : 0.00897932794359002,
            "width" : 0.04069767422146264,
            "x" : 0.1162790691877183,
            "y" : 0.13055555550794185
          },
          "confidence" : 0.3,
          "text" : "MAI HASIY"
        },
        {
          "bounding_box" : {
            "height" : 0.0029069765408833437,
            "width" : 0.042151158650716156,
            "x" : 0.11773255810196771,
            "y" : 0.14244186056676755
          },
          "confidence" : 0.3,
          "text" : "Widwmtd"
        },
        {
          "bounding_box" : {
            "height" : 0.00890986230638291,
            "width" : 0.04073774125840929,
            "x" : 0.44038694325211647,
            "y" : 0.13071948756080776
          },
          "confidence" : 0.3,
          "text" : "MaI Hosgiy"
        },
        {
          "bounding_box" : {
            "height" : 0.007267441749572834,
            "width" : 0.04651162465413411,
            "x" : 0.4404069791458011,
            "y" : 0.1409883722211437
          },
          "confidence" : 0.3,
          "text" : "SOIKACOETRALCRO"
        },
        {
          "bounding_box" : {
            "height" : 0.00897932794358991,
            "width" : 0.03924418555365661,
            "x" : 0.7645348834768053,
            "y" : 0.1305555555321667
          },
          "confidence" : 0.3,
          "text" : "Ww Honety"
        }
      ],
      "path" : "/Users/vladimirkuznetsov/SS Command Center/ss-control-center/data/audits/walmart-visual-pilot-snapshots/walmart-main-bbf179123bd9139dbe9e/derived/full-d33f58b819db518b6c7e2936b8551c1d842dbcb1aacdacf822c758aadd2a7140.jpg",
      "width" : 1800
    },
    {
      "height" : 2048,
      "observations" : [
        {
          "bounding_box" : {
            "height" : 0.05526566132903099,
            "width" : 0.19447720050811768,
            "x" : 0.3930355194883344,
            "y" : 0.8905848548472023
          },
          "confidence" : 0.3,
          "text" : "BEV PACKRO IВCPОLE8163"
        },
        {
          "bounding_box" : {
            "height" : 0.075581394135952,
            "width" : 0.25223612785339355,
            "x" : 0.3273703079774972,
            "y" : 0.8066860466981739
          },
          "confidence" : 1,
          "text" : "APSUCED"
        },
        {
          "bounding_box" : {
            "height" : 0.06989235058426857,
            "width" : 0.11449016057527983,
            "x" : 0.6797853313044888,
            "y" : 0.8212209318763181
          },
          "confidence" : 0.3,
          "text" : "ПР. р"
        },
        {
          "bounding_box" : {
            "height" : 0.03488371893763542,
            "width" : 0.07871198654174805,
            "x" : 0.6100178893170807,
            "y" : 0.8430232568829265
          },
          "confidence" : 0.3,
          "text" : "Bited"
        },
        {
          "bounding_box" : {
            "height" : 0.04505813866853714,
            "width" : 0.07692307692307693,
            "x" : 0.418604651332737,
            "y" : 0.7790697681003245
          },
          "confidence" : 1,
          "text" : "BUTTR"
        },
        {
          "bounding_box" : {
            "height" : 0.044989559799432755,
            "width" : 0.2957638593820426,
            "x" : 0.35211806820304087,
            "y" : 0.43608080131961713
          },
          "confidence" : 1,
          "text" : "PEPPERIDGE FARM"
        },
        {
          "bounding_box" : {
            "height" : 0.011627906933426857,
            "width" : 0.05366726105029768,
            "x" : 0.3774597499757456,
            "y" : 0.40843023252165866
          },
          "confidence" : 1,
          "text" : "EXTD."
        },
        {
          "bounding_box" : {
            "height" : 0.010373729281127453,
            "width" : 0.043004719110635525,
            "x" : 0.5688375326813367,
            "y" : 0.4097840655173264
          },
          "confidence" : 0.5,
          "text" : "3632"
        },
        {
          "bounding_box" : {
            "height" : 0.016124636866152287,
            "width" : 0.22361359229454625,
            "x" : 0.3881932054499668,
            "y" : 0.37645348835813275
          },
          "confidence" : 1,
          "text" : "BAKERY CLASSICS"
        },
        {
          "bounding_box" : {
            "height" : 0.042807698249816895,
            "width" : 0.2295343509087196,
            "x" : 0.35750474011159344,
            "y" : 0.16464266267146876
          },
          "confidence" : 1,
          "text" : "8 TOP SLICED"
        },
        {
          "bounding_box" : {
            "height" : 0.011855014599859715,
            "width" : 0.08586761584648717,
            "x" : 0.6332737061069122,
            "y" : 0.20494186054906738
          },
          "confidence" : 1,
          "text" : "MADE WITH"
        },
        {
          "bounding_box" : {
            "height" : 0.024826569482684135,
            "width" : 0.06983022964917707,
            "x" : 0.642186852758279,
            "y" : 0.1787204363657504
          },
          "confidence" : 1,
          "text" : "REAL"
        },
        {
          "bounding_box" : {
            "height" : 0.018895348533988,
            "width" : 0.08228980577909034,
            "x" : 0.4597495519504469,
            "y" : 0.15843023278242463
          },
          "confidence" : 1,
          "text" : "BUTTER"
        },
        {
          "bounding_box" : {
            "height" : 0.024950964376330376,
            "width" : 0.10026878577012288,
            "x" : 0.6260731211581685,
            "y" : 0.1510419597525472
          },
          "confidence" : 1,
          "text" : "BUTTER"
        },
        {
          "bounding_box" : {
            "height" : 0.0146484375,
            "width" : 0.13416815721071684,
            "x" : 0.4311270110413321,
            "y" : 0.1249999999759287
          },
          "confidence" : 1,
          "text" : "HOT DOG BUNS"
        },
        {
          "bounding_box" : {
            "height" : 0.010174418799579144,
            "width" : 0.16994632207430327,
            "x" : 0.3220035810245658,
            "y" : 0.09738372077826274
          },
          "confidence" : 0.3,
          "text" : "BIKaaMERTInY"
        },
        {
          "bounding_box" : {
            "height" : 0.01919894479215145,
            "width" : 0.11992881848261905,
            "x" : 0.31838979536037504,
            "y" : 0.06816215556573813
          },
          "confidence" : 0.3,
          "text" : "MEWI MOAiY"
        }
      ],
      "path" : "/Users/vladimirkuznetsov/SS Command Center/ss-control-center/data/audits/walmart-visual-pilot-snapshots/walmart-main-bbf179123bd9139dbe9e/derived/tile_front-f5343321446cbde8672bb423cacbe491ea8210353037cbd5b3cc9b3db48b4a8f.png",
      "width" : 1663
    },
    {
      "height" : 1010,
      "observations" : [
        {
          "bounding_box" : {
            "height" : 0.038235292340269234,
            "width" : 0.223837211728096,
            "x" : 0.38808139189757995,
            "y" : 0.9441176478004536
          },
          "confidence" : 1,
          "text" : "BAKERY CLASSICS"
        },
        {
          "bounding_box" : {
            "height" : 0.029821511070327045,
            "width" : 0.08433700352907181,
            "x" : 0.6337035910774709,
            "y" : 0.5145010095392482
          },
          "confidence" : 1,
          "text" : "MADE WITH"
        },
        {
          "bounding_box" : {
            "height" : 0.07305358282410268,
            "width" : 0.17491091787815094,
            "x" : 0.41254454195001344,
            "y" : 0.4502379139594489
          },
          "confidence" : 1,
          "text" : "TOP SLICED"
        },
        {
          "bounding_box" : {
            "height" : 0.07563024841912891,
            "width" : 0.07499999552965164,
            "x" : 0.6333333354851742,
            "y" : 0.44537815385766244
          },
          "confidence" : 1,
          "text" : "REAL"
        },
        {
          "bounding_box" : {
            "height" : 0.0823529385104037,
            "width" : 0.02616279013454914,
            "x" : 0.36046511649834007,
            "y" : 0.41470588427420996
          },
          "confidence" : 1,
          "text" : "8"
        },
        {
          "bounding_box" : {
            "height" : 0.050389835622050905,
            "width" : 0.08474148064851761,
            "x" : 0.45762926037622875,
            "y" : 0.3953933177069654
          },
          "confidence" : 1,
          "text" : "BUTTER"
        },
        {
          "bounding_box" : {
            "height" : 0.06870576461943068,
            "width" : 0.10439897328615189,
            "x" : 0.6207171803911011,
            "y" : 0.385815185752309
          },
          "confidence" : 1,
          "text" : "BUTTER"
        },
        {
          "bounding_box" : {
            "height" : 0.032352942287331654,
            "width" : 0.1366279125213623,
            "x" : 0.43023255612626976,
            "y" : 0.3176470584151577
          },
          "confidence" : 1,
          "text" : "HOT DOG BUNS"
        }
      ],
      "path" : "/Users/vladimirkuznetsov/SS Command Center/ss-control-center/data/audits/walmart-visual-pilot-snapshots/walmart-main-bbf179123bd9139dbe9e/derived/bottom_label-8b8ec1a506e4e3bc30d017798f72a3b7e93c8f916304be747e83ccab14ac96f6.png",
      "width" : 2048
    },
    {
      "height" : 1257,
      "observations" : [
        {
          "bounding_box" : {
            "height" : 0.1499999975741193,
            "width" : 0.6144067897209279,
            "x" : 0.3771186416437733,
            "y" : 0.604166668629607
          },
          "confidence" : 0.3,
          "text" : "E13PŞ|CED"
        },
        {
          "bounding_box" : {
            "height" : 0.09062003179650235,
            "width" : 0.1280388978930308,
            "x" : 0.7228525127375865,
            "y" : 0.5421303660283278
          },
          "confidence" : 1,
          "text" : "BUTTR"
        }
      ],
      "path" : "/Users/vladimirkuznetsov/SS Command Center/ss-control-center/data/audits/walmart-visual-pilot-snapshots/walmart-main-bbf179123bd9139dbe9e/derived/top_left_badge-f61a412d53f22fff6578efcf6f9a1e3ca7cbf498baef3d02321becd52749f8c8.png",
      "width" : 1233
    }
  ],
  "schema_version" : "walmart-local-ocr/v1"
}
